MANIFEST.in
README.md
setup.py
app_init_backend.egg-info/PKG-INFO
app_init_backend.egg-info/SOURCES.txt
app_init_backend.egg-info/dependency_links.txt
app_init_backend.egg-info/not-zip-safe
app_init_backend.egg-info/requires.txt
app_init_backend.egg-info/top_level.txt
webplatform_backend/__init__.py
webplatform_backend/webplatform-backend
webplatform_backend/app/__init__.py
webplatform_backend/app/app.py
webplatform_backend/app/gunicorn.py
webplatform_backend/app/jobs/__init__.py
webplatform_backend/app/jobs/runner.py
webplatform_backend/app/jobs/scheduler.py
webplatform_backend/app/lib/__init__.py
webplatform_backend/app/lib/applications/__init__.py
webplatform_backend/app/lib/applications/list.py
webplatform_backend/app/lib/files/__init__.py
webplatform_backend/app/lib/files/add.py
webplatform_backend/app/lib/files/attach.py
webplatform_backend/app/lib/files/download.py
webplatform_backend/app/lib/files/edit.py
webplatform_backend/app/lib/files/list.py
webplatform_backend/app/lib/files/meta.py
webplatform_backend/app/lib/files/notify.py
webplatform_backend/app/lib/files/remove.py
webplatform_backend/app/lib/imports/__init__.py
webplatform_backend/app/lib/imports/default.py
webplatform_backend/app/lib/jobs/__init__.py
webplatform_backend/app/lib/jobs/fib.py
webplatform_backend/app/lib/jobs/notify.py
webplatform_backend/app/lib/jobs/populate.py
webplatform_backend/app/lib/jobs/recover.py
webplatform_backend/app/lib/jobs/refresh.py
webplatform_backend/app/lib/jobs/scheduler.py
webplatform_backend/app/lib/jobs/stop.py
webplatform_backend/app/lib/jobs/test.py
webplatform_backend/app/lib/jobs/files/__init__.py
webplatform_backend/app/lib/jobs/files/unassigned.py
webplatform_backend/app/lib/jobs/interval/__init__.py
webplatform_backend/app/lib/jobs/interval/display.py
webplatform_backend/app/lib/jobs/interval/next.py
webplatform_backend/app/lib/jobs/notifications/__init__.py
webplatform_backend/app/lib/jobs/notifications/email.py
webplatform_backend/app/lib/jobs/results/__init__.py
webplatform_backend/app/lib/jobs/results/get.py
webplatform_backend/app/lib/jobs/results/list.py
webplatform_backend/app/lib/jobs/scheduled/__init__.py
webplatform_backend/app/lib/jobs/scheduled/add.py
